ferny/__init__.py
ferny/_version.py
ferny/errors.py
ferny/interaction_agent.py
ferny/interaction_client.py
ferny/session.py
ferny-0.dist-info/COPYING
ferny-0.dist-info/METADATA
ferny-0.dist-info/WHEEL
ferny-0.dist-info/top_level.txt
ferny-0.dist-info/RECORD
