Metadata-Version: 2.1
Name: ferny
Version: 0
Summary: A Python API wrapped around ssh(1)
Author-email: Allison Karlitskaya <allison.karlitskaya@redhat.com>
License: GNU GENERAL PUBLIC LICENSE
Project-URL: Home, https://github.com/allisonkarlitskaya/ferny/
Classifier: License :: OSI Approved :: GNU General Public License v3 or later (GPLv3+)
License-File: COPYING
